[
    {
      "orderID": 1,
      "date": "2022-09-01",
      "status": "Delivered",
      "orders": [
        {
          "productID": 156,
          "productName": "Кимчижигээ",
          "amount": 2,
          "price": 33400
        },
        { "productID": 586, 
        "productName": "Бүлгүги",
         "amount": 1, 
         "price": 15000 }
      ],
      "address": "СХД 40-р хороо нэг хотхон нэр байр нь",
      "phoneNumber":999999
    },
    {
      "orderID": 2,
      "date": "2022-09-02",
      "status": "Packed",
      "orders": [
        { "productID": 98," productName": "Кимчижигээ", "amount": 2, "price": 33400 },
        { "productID": 45," productName": "Бүлгүги", "amount": 1," price": 15000 }
      ],
      "address": "СХД 40-р хороо 2 хотхон нэр байр нь",
      "phoneNumber":999999
    },
    {
      "orderID": 3,
      "date": "2022-09-03",
      "status": "Mistaken",
      "orders": [
        { "productID": 156, "productName": "Кимчижигээ", "amount": 2, "price": 33400 },
        { "productID": 32, "productName": "Бүлгүги"," amount": 1, "price": 15000 }
      ],
      "address": "СХД 40-р хороо 3 хотхон нэр байр нь",
      "phoneNumber":999999
    },
    {
      "orderID": 4,
      "date": "2022-09-04",
      "status": "Delivered",
      "orders": [
        { "productID": 75, "productName": "Кимчижигээ", "amount": 2, "price": 33400 },
        { "productID": 596, "productName": "Бүлгүги", "amount": 1, "price": 15000 }
      ],
      "address": "СХД 40-р хороо 4 хотхон нэр байр нь",
      "phoneNumber":999999
    },
    {
      "orderID": 5,
      "date": "2022-09-05",
      "status": "Packed",
      "orders": [
        { "productID": 56, "productName": "Кимчижигээ", "amount": 2, "price": 33400 },
        { "productID": 54, "productName": "Бүлгүги", "amount": 1," price": 15000 }
      ],
      "address": "СХД 40-р хороо 5 хотхон нэр байр нь",
      "phoneNumber":999999
    }
  ]